{
  "project_info": {
    "project_number": "673104267676",
    "project_id": "myapp-boarding",
    "storage_bucket": "myapp-boarding.appspot.com"
  },
  "client": [
    {
      "client_info": {
        "mobilesdk_app_id": "1:673104267676:android:b9924d625547e5c6c52059",
        "android_client_info": {
          "package_name": "com.example.my_app"
        }
      },
      "oauth_client": [
        {
          "client_id": "673104267676-ngek36760315jiprf44cpbnh9hhnb3ik.apps.googleusercontent.com",
          "client_type": 3
        }
      ],
      "api_key": [
        {
          "current_key": "AIzaSyDPJoumvqs9m2dZHXUkSYDL1uJtHtdrAsk"
        }
      ],
      "services": {
        "appinvite_service": {
          "other_platform_oauth_client": [
            {
              "client_id": "673104267676-ngek36760315jiprf44cpbnh9hhnb3ik.apps.googleusercontent.com",
              "client_type": 3
            }
          ]
        }
      }
    }
  ],
  "configuration_version": "1"
}